ezfilelock/__init__.py
ezfilelock/filelock.py
ezfilelock/rwlock.py
ezfilelock/version.py
ezfilelock-1.0.1.dist-info/LICENSE
ezfilelock-1.0.1.dist-info/METADATA
ezfilelock-1.0.1.dist-info/WHEEL
ezfilelock-1.0.1.dist-info/top_level.txt
ezfilelock-1.0.1.dist-info/RECORD
