Metadata-Version: 2.1
Name: ezfilelock
Version: 1.0.1
Summary: A simple cross-platform file lock
Home-page: https://github.com/jinmingyi1998/ezfilelock
Author: Mingyi Jin
Author-email: jinmingyi1998@sina.cn
License: MIT License
Platform: UNKNOWN
License-File: LICENSE
